Metadata-Version: 1.1
Name: Alfred-Workflow
Version: 1.30
Summary: Full-featured helper library for writing Alfred 2/3 workflows
Home-page: http://www.deanishe.net/alfred-workflow/
Author: Dean Jackson
Author-email: deanishe@deanishe.net
License: UNKNOWN
Keywords: alfred workflow
Platform: UNKNOWN
Classifier: Development Status :: 5 - Production/Stable
Classifier: License :: OSI Approved :: MIT License
Classifier: Operating System :: MacOS :: MacOS X
Classifier: Intended Audience :: Developers
Classifier: Natural Language :: English
Classifier: Programming Language :: Python :: 2.6
Classifier: Programming Language :: Python :: 2.7
Classifier: Topic :: Software Development :: Libraries
Classifier: Topic :: Software Development :: Libraries :: Application Frameworks
